h4/__init__.py
h4-0.1.0.dist-info/LICENSE
h4-0.1.0.dist-info/METADATA
h4-0.1.0.dist-info/WHEEL
h4-0.1.0.dist-info/top_level.txt
h4-0.1.0.dist-info/RECORD
